[
    {
        "name": "private_beach_resort",
        "desc":{
            "it":"Stabilimento balneare privato",
            "en":"Private beach resort"
        },
        "objectId": "fwlROvUEy6",
        "type": "building",
        "value": 2
    },
    {
        "name": "kiosk",
        "objectId": "cIErnXsgaq",
        "iconURL": "https://raw.githubusercontent.com/driftyco/ionicons/master/png/512/nuclear.png",
        "type": "building",
        "value": 4
    },
    {
        "name": "disco",
        "objectId": "zxd35AkmZa",
        "type": "service",
        "value": 8
    },
    {
        "name": "toilet",
        "desc":{
            "it":"Bagno",
            "en":"Toilet"
        },
        "objectId": "Nthe0wzNyv",
        "type": "service",
        "value": 16
    },
    {
        "name": "parking",
        "desc":{
            "it":"Parcheggio",
            "en":"Parking"
        },
        "objectId": "lNvLK38vAa",
        "type": "service",
        "value": 32
    },
    {
        "name": "hospital",
        "desc":{
            "it":"Ospedale",
            "en":"Hospital"
        },
        "objectId": "QSpmoY8Q1J",
        "type": "building",
        "value": 64
    },
    {
        "name": "fuel",
        "desc":{
            "it":"Distributore di benzina",
            "en":"Gas Station"
        },
        "objectId": "kYNrSXGaU8",
        "type": "service",
        "value": 128
    },
    {
        "name": "sport",
        "objectId": "06NeJNScIa",
        "type": "service",
        "value": 256
    },
    {
        "name": "beach_resort",
        "objectId": "Q7X8yZqAAb",
        "type": "building",
        "value": 1
    },
    {
        "name": "garden",
        "objectId": "1rGBC6J8Mt",
        "type": "service",
        "value": 512
    },
    {
        "name": "mtb",
        "objectId": "WeHqeADmam",
        "type": "service",
        "value": 8192
    },
    {
        "name": "dog",
        "objectId": "ys8RoyCqUH",
        "type": "service",
        "value": 4096
    },
    {
        "name": "wifi",
        "desc":{
            "it":"Area Wi-Fi",
            "en":"Wi-Fi Area"
        },
        "objectId": "ftsVIEorfj",
        "type": "service",
        "value": 2048
    },
    {
        "name": "bus",
        "desc":{
            "it":"Fermata Autobus",
            "en":"Bus Stop"
        },
        "objectId": "XOMdgtiQ9h",
        "type": "service",
        "value": 1024
    }
]